newby/__init__.py
newby/__main__.py
newby/logging_config.ini
newby/newby.py
newby/templates.py
newby/loggers/__init__.py
newby/loggers/colored_formatter.py
newby/storage/__init__.py
newby/storage/storage.py
newby/utilities/__init__.py
newby/utilities/retrieve.py
newby-0.0.2.dist-info/licenses/LICENSE
newby-0.0.2.dist-info/METADATA
newby-0.0.2.dist-info/WHEEL
newby-0.0.2.dist-info/entry_points.txt
newby-0.0.2.dist-info/top_level.txt
newby-0.0.2.dist-info/RECORD
