Metadata-Version: 2.4
Name: newby
Version: 0.0.2
Summary: A tool for creating template projects.
Author-email: Janith Petangoda <jpetangoda@gmail.com>
License-Expression: MIT
Project-URL: Homepage, https://github.com/janithpet/newby
Project-URL: Issues, https://github.com/pypa/janithpet/newby/issues
Classifier: Programming Language :: Python :: 3
Classifier: Operating System :: OS Independent
Requires-Python: >=3.10
License-File: LICENSE
Dynamic: license-file
